{
  "nombre": "SE00770 Miel Para Flan",
  "subsidiaria": "SERVICIOS DE PASTELERIA S.A.",
  "elaboradoPor": "Mariela Barrantes Sánchez, Chef",
  "areaProduce": "Cocina",
  "areaEmpaca": "Empaque",
  "version": "03",
  "estado": "APROBADO",
  "ingredientes": [
    {
      "nombre": "Azucar Blanco Industrial",
      "cantidad": 19618,
      "unidad": null,
      "codigoNetSuite": "MP10074",
      "marca": null,
      "observaciones": null,
      "seccion": "Ensamble"
    },
    {
      "nombre": "Agua potable",
      "cantidad": 17040,
      "unidad": null,
      "codigoNetSuite": null,
      "marca": "FAS",
      "observaciones": null,
      "seccion": "Ensamble"
    }
  ],
  "pasos": [
    "Colocar en la marmita la azucar a 220° por 19 minutos (hasta que el caramelo este completamente desecho)",
    "Agregar el agua, cambiar programación para girar ambos lados en lapsos de 10.",
    "En el minuto 28 bajar la temperatura a 140° por 10 minutos más.",
    "Apagar, retirar de la marmita y dejar enfriar."
  ],
  "pesoTotalCantidad": 29250,
  "pesoTotalUnidad": "g",
  "tiempoPrepCantidad": 10,
  "tiempoPrepUnidad": "min",
  "porcionesCantidad": 1,
  "porcionesUnidad": "Tanda",
  "pesoPorcionCantidad": 29250,
  "pesoPorcionUnidad": "g",
  "mermaCantidad": 7408,
  "mermaUnidad": "g",
  "registroCambios": "Importación inicial desde Excel"
}
