{
  "nombre": "Torta Chocolate Grande Spoon (acetato)",
  "subsidiaria": "SERVICIOS DE PASTELERIA S.A.",
  "elaboradoPor": "Javier Tong, Chef",
  "areaProduce": "Decoración",
  "areaEmpaca": "Decoracion",
  "version": "01",
  "estado": "APROBADO",
  "ingredientes": [
    {
      "nombre": "ROSQUETE CHOCOLATE DAWN 600g",
      "cantidad": 765,
      "unidad": "g",
      "codigoNetSuite": "SE00464",
      "marca": "FAS",
      "observaciones": "1,5 UND",
      "seccion": "Ensamble"
    },
    {
      "nombre": "TRASVASADO LECHE CONDENSADA COCINADA",
      "cantidad": 460,
      "unidad": "g",
      "codigoNetSuite": "SE00386",
      "marca": "FAS",
      "observaciones": "1 1/2 TAZA",
      "seccion": "Ensamble"
    },
    {
      "nombre": "TRASVASADO LECHE CONDENSADA COCINADA",
      "cantidad": 460,
      "unidad": "g",
      "codigoNetSuite": "SE00387",
      "marca": "FAS",
      "observaciones": "1 1/2 TAZA",
      "seccion": "Ensamble"
    },
    {
      "nombre": "EMPAQUE FUDGE DE CHOCOLATE SPOON",
      "cantidad": 360,
      "unidad": "g",
      "codigoNetSuite": "SE00337",
      "marca": "FAS",
      "observaciones": "ENCREMADO",
      "seccion": "Decoración"
    },
    {
      "nombre": "EMPAQUE FUDGE DE CHOCOLATE SPOON",
      "cantidad": 220,
      "unidad": "g",
      "codigoNetSuite": "SE00337",
      "marca": "FAS",
      "observaciones": "COLOCHO BOQUIILA #127",
      "seccion": "Decoración"
    },
    {
      "nombre": "STICK DORADO (CAJA:100 UND)",
      "cantidad": 1,
      "unidad": "ud",
      "codigoNetSuite": "MP10011",
      "marca": "CHOCOLATE SOLUTIONS",
      "observaciones": null,
      "seccion": "Decoración"
    },
    {
      "nombre": "ACETATO ROLLO 8CMS x 10MTS",
      "cantidad": 75,
      "unidad": "cm",
      "codigoNetSuite": "EM10466",
      "marca": "TIPS",
      "observaciones": null,
      "seccion": "Decoración"
    },
    {
      "nombre": "Procesado de borona chocolate",
      "cantidad": 20,
      "unidad": "g",
      "codigoNetSuite": "SE00506",
      "marca": "FAS",
      "observaciones": null,
      "seccion": "Decoración"
    },
    {
      "nombre": "ORLA CARTON 10\" DORADA (UND)",
      "cantidad": 1,
      "unidad": "ud",
      "codigoNetSuite": "EM10008",
      "marca": "T",
      "observaciones": null,
      "seccion": "Empaque"
    },
    {
      "nombre": "QUEQUERA RED BASE/DOMO 10 (CAJA:50)",
      "cantidad": 1,
      "unidad": "ud",
      "codigoNetSuite": "EM10009",
      "marca": "MAYCA",
      "observaciones": null,
      "seccion": "Empaque"
    },
    {
      "nombre": "CINTA ADHESIVA TRANSPARENT 2*100 M (UND)",
      "cantidad": 60,
      "unidad": "cm",
      "codigoNetSuite": "EM10248",
      "marca": "ETIPLAST",
      "observaciones": null,
      "seccion": "Empaque"
    },
    {
      "nombre": "ETIQUETA BLANCA 2 5/8X1 15/16 (UND)",
      "cantidad": 1,
      "unidad": "ud",
      "codigoNetSuite": "EM10011",
      "marca": "ETIPLAST",
      "observaciones": null,
      "seccion": "Empaque"
    },
    {
      "nombre": "ETIQUETA BLANCA R-153 (UND)",
      "cantidad": 1,
      "unidad": "ud",
      "codigoNetSuite": "EM10124",
      "marca": "ETIPLAST",
      "observaciones": null,
      "seccion": "Empaque"
    },
    {
      "nombre": "ETIQ.BLANCA 1 1/4 * 3/4",
      "cantidad": 1,
      "unidad": "ud",
      "codigoNetSuite": "EM10002",
      "marca": "ETIPLAST",
      "observaciones": null,
      "seccion": "Empaque"
    }
  ],
  "pasos": [
    "1.- Se utilizan 1 1/5 de rosquete, cortarlos por la mitad y rellenar dos de ellos.",
    "2.- Rellenar con leche condensada cocinada cada mitad de rosquete y tapar.",
    "3.- Encremar con el fudge de chocolate y dejar liso.",
    "4.-Agregar en todo el borde el procesado de borona de chocolate y con el acetato cubrir toda la torta y pegar con un pedazo de cinta transparente.",
    "4.- Decorar con la boquilla #127 el colocho de fudge en toda la superficie y decorar con 1 stick dorado partido por la mitad, acorde a la foto.",
    "5.- Colocar la torta dentro del domo, etiquetar con etiqueta Spoon, nombre del producto y codigo de barras, y fecha de vencimiento."
  ],
  "pesoTotalCantidad": 2216,
  "pesoTotalUnidad": "g",
  "tiempoPrepCantidad": 9,
  "tiempoPrepUnidad": "Min.",
  "porcionesCantidad": 1,
  "porcionesUnidad": "ud",
  "pesoPorcionCantidad": 2216,
  "pesoPorcionUnidad": "g",
  "mermaCantidad": 145,
  "mermaUnidad": "g",
  "registroCambios": "Importación inicial desde Excel"
}
